csv2md/__init__.py
csv2md/__main__.py
csv2md/table.py
csv2md/test_table.py
csv2md/test_utils.py
csv2md/utils.py
csv2md_tddschn-1.3.1.dist-info/LICENSE
csv2md_tddschn-1.3.1.dist-info/METADATA
csv2md_tddschn-1.3.1.dist-info/WHEEL
csv2md_tddschn-1.3.1.dist-info/entry_points.txt
csv2md_tddschn-1.3.1.dist-info/RECORD
