Metadata-Version: 2.1
Name: csv2md-tddschn
Version: 1.3.1
Summary: Command line tool for converting CSV files into Markdown tables.
Home-page: https://github.com/tddschn/csv2md
License: MIT
Keywords: csv,markdown,convertor
Author: Teddy Xinyuan Chen
Author-email: 45612704+tddschn@users.noreply.github.com
Requires-Python: >=3.12,<4.0
Classifier: License :: OSI Approved :: MIT License
Classifier: Programming Language :: Python :: 3
Classifier: Programming Language :: Python :: 3.12
Classifier: Topic :: Utilities
Project-URL: Bug Tracker, https://github.com/tddschn/csv2md/issues
Project-URL: Repository, https://github.com/tddschn/csv2md
